{
  "updated": "2026-07-09",
  "store": "https://smartstore.naver.com/skillfulbrother",
  "cats": {
    "wireless": "무선 청소기",
    "wetdry": "건습식·유선 청소기",
    "fan": "선풍기",
    "heat": "히터·온풍기",
    "dehum": "제습기",
    "living": "주방·생활"
  },
  "models": [
    {
      "code": "BVC-H10",
      "aliases": [
        "CVC-H15"
      ],
      "name": "클래파 미니 핸디형 무선청소기",
      "cat": "wireless",
      "page": "products/bvc-h10.html",
      "manual": "manuals/BVC-H10.pdf",
      "parts": "https://smartstore.naver.com/skillfulbrother/search?q=BVC-H10",
      "store": "https://smartstore.naver.com/skillfulbrother/products/6999673131",
      "keywords": [
        "무선청소기",
        "청소기",
        "핸디형",
        "미니",
        "무선"
      ]
    },
    {
      "code": "BES-131W/CES-232W",
      "aliases": [
        "BES-131W",
        "CES-232W"
      ],
      "name": "클래파 스테인리스 2단 계란찜기",
      "cat": "living",
      "page": "products/bes-131w.html",
      "manual": "manuals/BES-131W_CES-232W.pdf",
      "parts": null,
      "store": "https://smartstore.naver.com/skillfulbrother/products/11255720719",
      "keywords": [
        "계란찜기"
      ]
    },
    {
      "code": "BMH-200R",
      "aliases": [],
      "name": "클래파 마이카 컨벡션 히터",
      "cat": "heat",
      "page": "products/bmh-200r.html",
      "manual": "manuals/BMH-200R.pdf",
      "parts": null,
      "store": "https://smartstore.naver.com/skillfulbrother/products/9317489531",
      "keywords": [
        "컨벡션 히터",
        "마이카",
        "히터"
      ]
    },
    {
      "code": "BVC-L138",
      "aliases": [],
      "name": "클래파 대용량 30L 건습식 청소기",
      "cat": "wetdry",
      "page": "products/bvc-l138.html",
      "manual": "manuals/BVC-L138.pdf",
      "parts": "https://smartstore.naver.com/skillfulbrother/search?q=BVC-L138",
      "store": "https://smartstore.naver.com/skillfulbrother/products/7972371336",
      "keywords": [
        "건습식 청소기",
        "건습식",
        "청소기",
        "대용량"
      ]
    },
    {
      "code": "BEF-C156W",
      "aliases": [],
      "name": "클래파 멀티 무선 선풍기",
      "cat": "fan",
      "page": "products/bef-c156w.html",
      "manual": "manuals/BEF-C156W.pdf",
      "parts": "https://smartstore.naver.com/skillfulbrother/products/12166003860",
      "store": "https://smartstore.naver.com/skillfulbrother/products/11956269278",
      "keywords": [
        "무선 선풍기",
        "선풍기",
        "무선",
        "에어제로",
        "air zero"
      ],
      "label": "본체 하단 (배터리 커버 부근)"
    },
    {
      "code": "BVC-S185",
      "aliases": [
        "CVC-S230"
      ],
      "name": "클래파 스탠딩 슬림 무선 청소기",
      "cat": "wireless",
      "page": "products/bvc-s185.html",
      "manual": "manuals/BVC-S185.pdf",
      "parts": "https://smartstore.naver.com/skillfulbrother/search?q=BVC-S185",
      "store": "https://smartstore.naver.com/skillfulbrother/products/11901197610",
      "keywords": [
        "청소기",
        "슬림",
        "무선",
        "더라이트"
      ]
    },
    {
      "code": "BEF-D400",
      "aliases": [
        "BEF-D400W",
        "BEF-D400M",
        "BEF-D400B",
        "BDF-C400"
      ],
      "name": "클래파 탁상용 무선 선풍기",
      "cat": "fan",
      "page": "products/bef-d400.html",
      "manual": "manuals/BEF-D400.pdf",
      "parts": null,
      "store": "https://smartstore.naver.com/skillfulbrother/products/11574521856",
      "keywords": [
        "무선 선풍기",
        "선풍기",
        "무선"
      ]
    },
    {
      "code": "CEK-S220",
      "aliases": [
        "BEK-120P"
      ],
      "name": "클래파 분리형 프리볼트 멀티포트",
      "cat": "living",
      "page": "products/cek-s220.html",
      "manual": "manuals/CEK-S220_BEK-120P.pdf",
      "parts": null,
      "store": "https://smartstore.naver.com/skillfulbrother/products/11325093921",
      "keywords": [
        "멀티포트"
      ]
    },
    {
      "code": "BYF-G18",
      "aliases": [],
      "name": "클래파 대용량 그릭요거트 메이커",
      "cat": "living",
      "page": "products/byf-g18.html",
      "manual": "manuals/BYF-G18.pdf",
      "parts": "https://smartstore.naver.com/skillfulbrother/search?q=BYF-G18",
      "store": "https://smartstore.naver.com/skillfulbrother/products/7982599204",
      "keywords": [
        "그릭요거트",
        "요거트",
        "대용량"
      ]
    },
    {
      "code": "BWF-200T",
      "aliases": [],
      "name": "클래파 휴대용 구강세정기",
      "cat": "living",
      "page": "products/bwf-200t.html",
      "manual": "manuals/BWF-200T.pdf",
      "parts": null,
      "store": "https://smartstore.naver.com/skillfulbrother/products/10704009364",
      "keywords": [
        "구강세정기"
      ]
    },
    {
      "code": "BED-611L",
      "aliases": [
        "CED-L611"
      ],
      "name": "클래파 저소음 제습기 11L",
      "cat": "dehum",
      "page": "products/bed-611l.html",
      "manual": "manuals/BED-611L_CED-L611.pdf",
      "parts": null,
      "store": "https://smartstore.naver.com/skillfulbrother/products/11904464766",
      "keywords": [
        "제습기",
        "저소음"
      ]
    },
    {
      "code": "BHF-8000W",
      "aliases": [
        "BHF-8000KK"
      ],
      "name": "클래파 보조배터리 겸용 핸디 에어건",
      "cat": "fan",
      "page": "products/bhf-8000w.html",
      "manual": "manuals/BHF-8000W.pdf",
      "parts": "https://smartstore.naver.com/skillfulbrother/products/10311125246",
      "store": "https://smartstore.naver.com/skillfulbrother/products/10248748515",
      "keywords": [
        "에어건"
      ]
    },
    {
      "code": "BVC-H38",
      "aliases": [
        "BVC-H22",
        "CVC-H17",
        "NVC-Y01"
      ],
      "name": "클래파 AI 흡입 무선 청소기 400W",
      "cat": "wireless",
      "page": "products/bvc-h38.html",
      "manual": "manuals/BVC-H38.pdf",
      "parts": "https://smartstore.naver.com/skillfulbrother/search?q=BVC-H38",
      "store": "https://smartstore.naver.com/skillfulbrother/products/12733553580",
      "keywords": [
        "청소기",
        "무선"
      ],
      "label": "탈착식 배터리팩에 부착"
    },
    {
      "code": "BVC-T500W",
      "aliases": [],
      "name": "클래파 엘리트 타워 무선청소기",
      "cat": "wireless",
      "page": "products/bvc-t500w.html",
      "manual": "manuals/BVC-T500W.pdf",
      "parts": "https://smartstore.naver.com/skillfulbrother/search?q=BVC-T500W",
      "store": "https://smartstore.naver.com/skillfulbrother/products/10738911598",
      "keywords": [
        "무선청소기",
        "청소기",
        "타워",
        "무선"
      ]
    },
    {
      "code": "BVC-L125",
      "aliases": [],
      "name": "클래파 대용량 25L 건습식 청소기",
      "cat": "wetdry",
      "page": "products/bvc-l125.html",
      "manual": "manuals/BVC-L125.pdf",
      "parts": "https://smartstore.naver.com/skillfulbrother/search?q=BVC-L125",
      "store": null,
      "keywords": [
        "건습식 청소기",
        "건습식",
        "청소기",
        "대용량"
      ]
    },
    {
      "code": "BVC-C13K",
      "aliases": [],
      "name": "클래파 차량용 무선 청소기",
      "cat": "wireless",
      "page": "products/bvc-c13k.html",
      "manual": "manuals/BVC-C13K.pdf",
      "parts": "https://smartstore.naver.com/skillfulbrother/search?q=BVC-C13K",
      "store": "https://smartstore.naver.com/skillfulbrother/products/9250938742",
      "keywords": [
        "차량용",
        "청소기",
        "무선"
      ]
    },
    {
      "code": "BFB-VC120",
      "aliases": [],
      "name": "클래파 싸이클론 무선 청소기",
      "cat": "wireless",
      "page": "products/bfb-vc120.html",
      "manual": "manuals/BFB-VC120.pdf",
      "parts": "https://smartstore.naver.com/skillfulbrother/search?q=BFB-VC120",
      "store": null,
      "keywords": [
        "청소기",
        "무선"
      ],
      "label": "바닥 브러시·배터리에 부품별 부착"
    },
    {
      "code": "IB-VC0601",
      "aliases": [],
      "name": "클래파 유선 진공청소기",
      "cat": "wetdry",
      "page": "products/ib-vc0601.html",
      "manual": "manuals/IB-VC0601.pdf",
      "parts": "https://smartstore.naver.com/skillfulbrother/search?q=IB-VC0601",
      "store": null,
      "keywords": [
        "진공청소기",
        "청소기"
      ]
    },
    {
      "code": "BHF-360W",
      "aliases": [],
      "name": "클래파 냉각 휴대용 선풍기",
      "cat": "fan",
      "page": "products/bhf-360w.html",
      "manual": "manuals/BHF-360W.pdf",
      "parts": null,
      "store": "https://smartstore.naver.com/skillfulbrother/products/11601702825",
      "keywords": [
        "선풍기",
        "냉각"
      ]
    },
    {
      "code": "BHH-2000S",
      "aliases": [],
      "name": "클래파 하이라이트 전기 히터",
      "cat": "heat",
      "page": "products/bhh-2000s.html",
      "manual": "manuals/BHH-2000S.pdf",
      "parts": null,
      "store": "https://smartstore.naver.com/skillfulbrother/products/9353650568",
      "keywords": [
        "히터"
      ]
    },
    {
      "code": "BPH-W181",
      "aliases": [
        "CPH-W181G"
      ],
      "name": "클래파 욕실 난방기",
      "cat": "heat",
      "page": "products/bph-w181.html",
      "manual": "manuals/BPH-W181.pdf",
      "parts": null,
      "store": "https://smartstore.naver.com/skillfulbrother/products/7115825768",
      "keywords": [
        "욕실",
        "난방기"
      ]
    },
    {
      "code": "BOH-235",
      "aliases": [],
      "name": "클래파 카본 오방난로",
      "cat": "heat",
      "page": "products/boh-235.html",
      "manual": "manuals/BOH-235.pdf",
      "parts": null,
      "store": "https://smartstore.naver.com/skillfulbrother/products/11043260778",
      "keywords": [
        "난로"
      ]
    },
    {
      "code": "BFB-PH180W",
      "aliases": [],
      "name": "클래파 프리미엄 ECO PTC 온풍기",
      "cat": "heat",
      "page": "products/bfb-ph180w.html",
      "manual": null,
      "parts": null,
      "store": "https://smartstore.naver.com/skillfulbrother/products/9574170549",
      "keywords": [
        "온풍기"
      ]
    },
    {
      "code": "BRC-30W",
      "aliases": [],
      "name": "클래파 미니밥솥",
      "cat": "living",
      "page": "products/brc-30w.html",
      "manual": "manuals/BRC-30W.pdf",
      "parts": null,
      "store": "https://smartstore.naver.com/skillfulbrother/products/9810723609",
      "keywords": [
        "미니"
      ]
    },
    {
      "code": "BMD-656",
      "aliases": [],
      "name": "클래파 미니 제습기",
      "cat": "dehum",
      "page": null,
      "manual": null,
      "parts": null,
      "store": "https://smartstore.naver.com/skillfulbrother/products/10302008839",
      "keywords": [
        "미니 제습기",
        "제습기",
        "습기",
        "제습"
      ]
    },
    {
      "code": "CHD-D16G",
      "aliases": [],
      "name": "클래파 BLDC 드라이기",
      "cat": "living",
      "page": null,
      "manual": null,
      "parts": null,
      "store": "https://smartstore.naver.com/skillfulbrother/products/10833395664",
      "keywords": [
        "드라이기",
        "헤어드라이어",
        "드라이어",
        "BLDC"
      ],
      "label": "전원 코드에 부착된 라벨 태그"
    },
    {
      "code": "BFB-VC170",
      "aliases": [
        "BFB-VC160"
      ],
      "name": "클래파 무선청소기 전용 구성품 (BFB-VC170)",
      "cat": "wireless",
      "page": null,
      "manual": null,
      "parts": "https://smartstore.naver.com/skillfulbrother/products/10228033078",
      "store": "https://smartstore.naver.com/skillfulbrother/products/10228033078",
      "keywords": [
        "구성품",
        "부품"
      ]
    }
  ]
}